connector/__init__.py
connector/main.py
mcp_fivetran/__init__.py
mcp_fivetran/main.py
mcp_fivetran_fastmcp-0.1.1.dist-info/METADATA
mcp_fivetran_fastmcp-0.1.1.dist-info/WHEEL
mcp_fivetran_fastmcp-0.1.1.dist-info/entry_points.txt
mcp_fivetran_fastmcp-0.1.1.dist-info/top_level.txt
mcp_fivetran_fastmcp-0.1.1.dist-info/RECORD
