Metadata-Version: 2.4
Name: mcp-fivetran-fastmcp
Version: 0.1.1
Summary: MCP Server for FiveTran
Project-URL: Homepage, https://github.com/fastmcp-me/mcp_fivetran#readme
Project-URL: Repository, https://github.com/fastmcp-me/mcp_fivetran.git
Project-URL: Issues, https://github.com/fastmcp-me/mcp_fivetran/issues
Requires-Python: >=3.12.8
Requires-Dist: fivetran-connector-sdk>=1.4.0
Requires-Dist: mcp[cli]>=1.7.1
Requires-Dist: python-dotenv>=1.1.0
Requires-Dist: requests>=2.32.3
